MANIFEST.in
README.rst
setup.py
css/__init__.py
css.fontawesome.egg-info/PKG-INFO
css.fontawesome.egg-info/SOURCES.txt
css.fontawesome.egg-info/dependency_links.txt
css.fontawesome.egg-info/entry_points.txt
css.fontawesome.egg-info/namespace_packages.txt
css.fontawesome.egg-info/not-zip-safe
css.fontawesome.egg-info/requires.txt
css.fontawesome.egg-info/top_level.txt
css/fontawesome/__init__.py
css/fontawesome/resources/README.md
css/fontawesome/resources/css/font-awesome-ie7.min.css
css/fontawesome/resources/css/font-awesome.css
css/fontawesome/resources/css/font-awesome.min.css
css/fontawesome/resources/docs/design.html
css/fontawesome/resources/docs/index.html
css/fontawesome/resources/docs/test.html
css/fontawesome/resources/docs/assets/css/font-awesome-ie7.min.css
css/fontawesome/resources/docs/assets/css/font-awesome.css
css/fontawesome/resources/docs/assets/css/font-awesome.min.css
css/fontawesome/resources/docs/assets/css/prettify.css
css/fontawesome/resources/docs/assets/css/site.css
css/fontawesome/resources/docs/assets/font/FontAwesome.otf
css/fontawesome/resources/docs/assets/font/fontawesome-webfont.eot
css/fontawesome/resources/docs/assets/font/fontawesome-webfont.svg
css/fontawesome/resources/docs/assets/font/fontawesome-webfont.ttf
css/fontawesome/resources/docs/assets/font/fontawesome-webfont.woff
css/fontawesome/resources/docs/assets/font/museo_slab_300-webfont.eot
css/fontawesome/resources/docs/assets/font/museo_slab_300-webfont.ttf
css/fontawesome/resources/docs/assets/font/museo_slab_500-webfont.eot
css/fontawesome/resources/docs/assets/font/museo_slab_500-webfont.ttf
css/fontawesome/resources/docs/assets/font/proximanova-sbold-webfont.eot
css/fontawesome/resources/docs/assets/font/proximanova-sbold-webfont.ttf
css/fontawesome/resources/docs/assets/font/proximanova-webfont.eot
css/fontawesome/resources/docs/assets/font/proximanova-webfont.ttf
css/fontawesome/resources/docs/assets/ico/favicon.ico
css/fontawesome/resources/docs/assets/img/contribution-sample.png
css/fontawesome/resources/docs/assets/img/fort_awesome.jpg
css/fontawesome/resources/docs/assets/img/glyphicons-halflings-white.png
css/fontawesome/resources/docs/assets/img/glyphicons-halflings.png
css/fontawesome/resources/docs/assets/img/icon-flag.pdf
