Metadata-Version: 1.0
Name: css.fontawesome
Version: 3.0
Summary: fanstatic font awesome
Home-page: https://github.com/jkoelker/css.fontawesome
Author: Jason Kölker
Author-email: jason@koelker.net
License: CC BY 3.0
Keywords: fanstatic bootstrap font-awesome fontawesome
Platform: UNKNOWN
